{"MAIN"             :{"cheatcode"     :"AIC",
                      "command"       :"aic",
                      "language"      :"RU",
                      "main_active"   :true,
                      "standard_icons":false},
 "ak47_anim"        :{"customX1"        :-14,
                      "customX2"        :-41,
                      "customY1"        :0,
                      "customY2"        :-34,
                      "delay"           :0,
                      "delay_replay"    :0,
                      "delay_replay_end":0,
                      "foreground"      :false,
                      "outline"         :false,
                      "posH"            :58,
                      "posW"            :47,
                      "posX"            :509,
                      "posY"            :16},
 "bat_anim"         :{"customX1"        :-14,
                      "customX2"        :-41,
                      "customY1"        :0,
                      "customY2"        :-34,
                      "delay"           :0,
                      "delay_replay"    :0,
                      "delay_replay_end":0,
                      "foreground"      :false,
                      "outline"         :false,
                      "posH"            :58,
                      "posW"            :47,
                      "posX"            :509,
                      "posY"            :16},
 "bomb_anim"        :{"customX1"        :-14,
                      "customX2"        :-41,
                      "customY1"        :0,
                      "customY2"        :-34,
                      "delay"           :0,
                      "delay_replay"    :0,
                      "delay_replay_end":0,
                      "foreground"      :false,
                      "outline"         :false,
                      "posH"            :58,
                      "posW"            :47,
                      "posX"            :509,
                      "posY"            :16},
 "brassknuckle_anim":{"customX1"        :-14,
                      "customX2"        :-41,
                      "customY1"        :0,
                      "customY2"        :-34,
                      "delay"           :0,
                      "delay_replay"    :0,
                      "delay_replay_end":0,
                      "foreground"      :false,
                      "outline"         :false,
                      "posH"            :58,
                      "posW"            :47,
                      "posX"            :509,
                      "posY"            :16},
 "camera_anim"      :{"customX1"        :-14,
                      "customX2"        :-41,
                      "customY1"        :0,
                      "customY2"        :-34,
                      "delay"           :0,
                      "delay_replay"    :0,
                      "delay_replay_end":0,
                      "foreground"      :false,
                      "outline"         :false,
                      "posH"            :58,
                      "posW"            :47,
                      "posX"            :509,
                      "posY"            :16},
 "chnsaw_anim"      :{"customX1"        :-14,
                      "customX2"        :-41,
                      "customY1"        :0,
                      "customY2"        :-34,
                      "delay"           :0,
                      "delay_replay"    :0,
                      "delay_replay_end":0,
                      "foreground"      :false,
                      "outline"         :false,
                      "posH"            :58,
                      "posW"            :47,
                      "posX"            :509,
                      "posY"            :16},
 "chromegun_anim"   :{"customX1"        :-14,
                      "customX2"        :-41,
                      "customY1"        :0,
                      "customY2"        :-34,
                      "delay"           :0,
                      "delay_replay"    :0,
                      "delay_replay_end":0,
                      "foreground"      :false,
                      "outline"         :false,
                      "posH"            :58,
                      "posW"            :47,
                      "posX"            :509,
                      "posY"            :16},
 "colt45_anim"      :{"customX1"        :-14,
                      "customX2"        :-41,
                      "customY1"        :0,
                      "customY2"        :-34,
                      "delay"           :0,
                      "delay_replay"    :0,
                      "delay_replay_end":0,
                      "foreground"      :false,
                      "outline"         :false,
                      "posH"            :58,
                      "posW"            :47,
                      "posX"            :509,
                      "posY"            :16},
 "cuntgun_anim"     :{"customX1"        :-14,
                      "customX2"        :-41,
                      "customY1"        :0,
                      "customY2"        :-34,
                      "delay"           :0,
                      "delay_replay"    :0,
                      "delay_replay_end":0,
                      "foreground"      :false,
                      "outline"         :false,
                      "posH"            :58,
                      "posW"            :47,
                      "posX"            :509,
                      "posY"            :16},
 "desert_eagle_anim":{"customX1"        :-14,
                      "customX2"        :-41,
                      "customY1"        :0,
                      "customY2"        :-34,
                      "delay"           :0,
                      "delay_replay"    :0,
                      "delay_replay_end":0,
                      "foreground"      :false,
                      "outline"         :false,
                      "posH"            :58,
                      "posW"            :47,
                      "posX"            :509,
                      "posY"            :16},
 "fire_ex_anim"     :{"customX1"        :-14,
                      "customX2"        :-41,
                      "customY1"        :0,
                      "customY2"        :-34,
                      "delay"           :0,
                      "delay_replay"    :0,
                      "delay_replay_end":0,
                      "foreground"      :false,
                      "outline"         :false,
                      "posH"            :58,
                      "posW"            :47,
                      "posX"            :509,
                      "posY"            :16},
 "fist_anim"        :{"customX1"        :0,
                      "customX2"        :-11,
                      "customY1"        :0,
                      "customY2"        :-16,
                      "delay"           :15,
                      "delay_replay"    :0,
                      "delay_replay_end":0,
                      "foreground"      :false,
                      "outline"         :false,
                      "posH"            :58,
                      "posW"            :47,
                      "posX"            :509,
                      "posY"            :16},
 "flame_anim"       :{"customX1"        :-14,
                      "customX2"        :-41,
                      "customY1"        :0,
                      "customY2"        :-34,
                      "delay"           :0,
                      "delay_replay"    :0,
                      "delay_replay_end":0,
                      "foreground"      :false,
                      "outline"         :false,
                      "posH"            :58,
                      "posW"            :47,
                      "posX"            :509,
                      "posY"            :16},
 "flowera_anim"     :{"customX1"        :-14,
                      "customX2"        :-41,
                      "customY1"        :0,
                      "customY2"        :-34,
                      "delay"           :0,
                      "delay_replay"    :0,
                      "delay_replay_end":0,
                      "foreground"      :false,
                      "outline"         :false,
                      "posH"            :58,
                      "posW"            :47,
                      "posX"            :509,
                      "posY"            :16},
 "golfclub_anim"    :{"customX1"        :-14,
                      "customX2"        :-41,
                      "customY1"        :0,
                      "customY2"        :-34,
                      "delay"           :0,
                      "delay_replay"    :0,
                      "delay_replay_end":0,
                      "foreground"      :false,
                      "outline"         :false,
                      "posH"            :58,
                      "posW"            :47,
                      "posX"            :509,
                      "posY"            :16},
 "grenade_anim"     :{"customX1"        :-14,
                      "customX2"        :-41,
                      "customY1"        :0,
                      "customY2"        :-34,
                      "delay"           :0,
                      "delay_replay"    :0,
                      "delay_replay_end":0,
                      "foreground"      :false,
                      "outline"         :false,
                      "posH"            :58,
                      "posW"            :47,
                      "posX"            :509,
                      "posY"            :16},
 "gun_cane_anim"    :{"customX1"        :-14,
                      "customX2"        :-41,
                      "customY1"        :0,
                      "customY2"        :-34,
                      "delay"           :0,
                      "delay_replay"    :0,
                      "delay_replay_end":0,
                      "foreground"      :false,
                      "outline"         :false,
                      "posH"            :58,
                      "posW"            :47,
                      "posX"            :509,
                      "posY"            :16},
 "gun_dildo1_anim"  :{"customX1"        :-14,
                      "customX2"        :-41,
                      "customY1"        :0,
                      "customY2"        :-34,
                      "delay"           :0,
                      "delay_replay"    :0,
                      "delay_replay_end":0,
                      "foreground"      :false,
                      "outline"         :false,
                      "posH"            :58,
                      "posW"            :47,
                      "posX"            :509,
                      "posY"            :16},
 "gun_dildo2_anim"  :{"customX1"        :-14,
                      "customX2"        :-41,
                      "customY1"        :0,
                      "customY2"        :-34,
                      "delay"           :0,
                      "delay_replay"    :0,
                      "delay_replay_end":0,
                      "foreground"      :false,
                      "outline"         :false,
                      "posH"            :58,
                      "posW"            :47,
                      "posX"            :509,
                      "posY"            :16},
 "gun_para_anim"    :{"customX1"        :-14,
                      "customX2"        :-41,
                      "customY1"        :0,
                      "customY2"        :-34,
                      "delay"           :0,
                      "delay_replay"    :0,
                      "delay_replay_end":0,
                      "foreground"      :false,
                      "outline"         :false,
                      "posH"            :58,
                      "posW"            :47,
                      "posX"            :509,
                      "posY"            :16},
 "gun_vibe1_anim"   :{"customX1"        :-14,
                      "customX2"        :-41,
                      "customY1"        :0,
                      "customY2"        :-34,
                      "delay"           :0,
                      "delay_replay"    :0,
                      "delay_replay_end":0,
                      "foreground"      :false,
                      "outline"         :false,
                      "posH"            :58,
                      "posW"            :47,
                      "posX"            :509,
                      "posY"            :16},
 "gun_vibe2_anim"   :{"customX1"        :-14,
                      "customX2"        :-41,
                      "customY1"        :0,
                      "customY2"        :-34,
                      "delay"           :0,
                      "delay_replay"    :0,
                      "delay_replay_end":0,
                      "foreground"      :false,
                      "outline"         :false,
                      "posH"            :58,
                      "posW"            :47,
                      "posX"            :509,
                      "posY"            :16},
 "heatseek_anim"    :{"customX1"        :-14,
                      "customX2"        :-41,
                      "customY1"        :0,
                      "customY2"        :-34,
                      "delay"           :0,
                      "delay_replay"    :0,
                      "delay_replay_end":0,
                      "foreground"      :false,
                      "outline"         :false,
                      "posH"            :58,
                      "posW"            :47,
                      "posX"            :509,
                      "posY"            :16},
 "irgoggles_anim"   :{"customX1"        :-14,
                      "customX2"        :-41,
                      "customY1"        :0,
                      "customY2"        :-34,
                      "delay"           :0,
                      "delay_replay"    :0,
                      "delay_replay_end":0,
                      "foreground"      :false,
                      "outline"         :false,
                      "posH"            :58,
                      "posW"            :47,
                      "posX"            :509,
                      "posY"            :16},
 "katana_anim"      :{"customX1"        :-14,
                      "customX2"        :-41,
                      "customY1"        :0,
                      "customY2"        :-34,
                      "delay"           :0,
                      "delay_replay"    :0,
                      "delay_replay_end":0,
                      "foreground"      :false,
                      "outline"         :false,
                      "posH"            :58,
                      "posW"            :47,
                      "posX"            :509,
                      "posY"            :16},
 "knifecur_anim"    :{"customX1"        :-14,
                      "customX2"        :-41,
                      "customY1"        :0,
                      "customY2"        :-34,
                      "delay"           :0,
                      "delay_replay"    :0,
                      "delay_replay_end":0,
                      "foreground"      :false,
                      "outline"         :false,
                      "posH"            :58,
                      "posW"            :47,
                      "posX"            :509,
                      "posY"            :16},
 "m4_anim"          :{"customX1"        :-14,
                      "customX2"        :-41,
                      "customY1"        :0,
                      "customY2"        :-34,
                      "delay"           :0,
                      "delay_replay"    :0,
                      "delay_replay_end":0,
                      "foreground"      :false,
                      "outline"         :false,
                      "posH"            :58,
                      "posW"            :47,
                      "posX"            :509,
                      "posY"            :16},
 "micro_uzi_anim"   :{"customX1"        :-14,
                      "customX2"        :-41,
                      "customY1"        :0,
                      "customY2"        :-34,
                      "delay"           :0,
                      "delay_replay"    :0,
                      "delay_replay_end":0,
                      "foreground"      :false,
                      "outline"         :false,
                      "posH"            :58,
                      "posW"            :47,
                      "posX"            :509,
                      "posY"            :16},
 "minigun_anim"     :{"customX1"        :-14,
                      "customX2"        :-41,
                      "customY1"        :0,
                      "customY2"        :-34,
                      "delay"           :0,
                      "delay_replay"    :0,
                      "delay_replay_end":0,
                      "foreground"      :false,
                      "outline"         :false,
                      "posH"            :58,
                      "posW"            :47,
                      "posX"            :509,
                      "posY"            :16},
 "molotov_anim"     :{"customX1"        :-14,
                      "customX2"        :-41,
                      "customY1"        :0,
                      "customY2"        :-34,
                      "delay"           :0,
                      "delay_replay"    :0,
                      "delay_replay_end":0,
                      "foreground"      :false,
                      "outline"         :false,
                      "posH"            :58,
                      "posW"            :47,
                      "posX"            :509,
                      "posY"            :16},
 "mp5lng_anim"      :{"customX1"        :-14,
                      "customX2"        :-41,
                      "customY1"        :0,
                      "customY2"        :-34,
                      "delay"           :0,
                      "delay_replay"    :0,
                      "delay_replay_end":0,
                      "foreground"      :false,
                      "outline"         :false,
                      "posH"            :58,
                      "posW"            :47,
                      "posX"            :509,
                      "posY"            :16},
 "nitestick_anim"   :{"customX1"        :-14,
                      "customX2"        :-41,
                      "customY1"        :0,
                      "customY2"        :-34,
                      "delay"           :0,
                      "delay_replay"    :0,
                      "delay_replay_end":0,
                      "foreground"      :false,
                      "outline"         :false,
                      "posH"            :58,
                      "posW"            :47,
                      "posX"            :509,
                      "posY"            :16},
 "nvgoggles_anim"   :{"customX1"        :-14,
                      "customX2"        :-41,
                      "customY1"        :0,
                      "customY2"        :-34,
                      "delay"           :0,
                      "delay_replay"    :0,
                      "delay_replay_end":0,
                      "foreground"      :false,
                      "outline"         :false,
                      "posH"            :58,
                      "posW"            :47,
                      "posX"            :509,
                      "posY"            :16},
 "outline_anim"     :{"customX1"        :0,
                      "customX2"        :-41,
                      "customY1"        :0,
                      "customY2"        :-34,
                      "delay"           :0,
                      "delay_replay"    :0,
                      "delay_replay_end":0,
                      "foreground"      :false,
                      "outline"         :true,
                      "posH"            :58,
                      "posW"            :47,
                      "posX"            :509,
                      "posY"            :16},
 "poolcue_anim"     :{"customX1"        :-14,
                      "customX2"        :-41,
                      "customY1"        :0,
                      "customY2"        :-34,
                      "delay"           :0,
                      "delay_replay"    :0,
                      "delay_replay_end":0,
                      "foreground"      :false,
                      "outline"         :false,
                      "posH"            :58,
                      "posW"            :47,
                      "posX"            :509,
                      "posY"            :16},
 "rocketla_anim"    :{"customX1"        :-14,
                      "customX2"        :-41,
                      "customY1"        :0,
                      "customY2"        :-34,
                      "delay"           :0,
                      "delay_replay"    :0,
                      "delay_replay_end":0,
                      "foreground"      :false,
                      "outline"         :false,
                      "posH"            :58,
                      "posW"            :47,
                      "posX"            :509,
                      "posY"            :16},
 "satchel_anim"     :{"customX1"        :-14,
                      "customX2"        :-41,
                      "customY1"        :0,
                      "customY2"        :-34,
                      "delay"           :0,
                      "delay_replay"    :0,
                      "delay_replay_end":0,
                      "foreground"      :false,
                      "outline"         :false,
                      "posH"            :58,
                      "posW"            :47,
                      "posX"            :509,
                      "posY"            :16},
 "sawnoff_anim"     :{"customX1"        :-14,
                      "customX2"        :-41,
                      "customY1"        :0,
                      "customY2"        :-34,
                      "delay"           :0,
                      "delay_replay"    :0,
                      "delay_replay_end":0,
                      "foreground"      :false,
                      "outline"         :false,
                      "posH"            :58,
                      "posW"            :47,
                      "posX"            :509,
                      "posY"            :16},
 "shotgspa_anim"    :{"customX1"        :-14,
                      "customX2"        :-41,
                      "customY1"        :0,
                      "customY2"        :-34,
                      "delay"           :0,
                      "delay_replay"    :0,
                      "delay_replay_end":0,
                      "foreground"      :false,
                      "outline"         :false,
                      "posH"            :58,
                      "posW"            :47,
                      "posX"            :509,
                      "posY"            :16},
 "shovel_anim"      :{"customX1"        :-14,
                      "customX2"        :-41,
                      "customY1"        :0,
                      "customY2"        :-34,
                      "delay"           :0,
                      "delay_replay"    :0,
                      "delay_replay_end":0,
                      "foreground"      :false,
                      "outline"         :false,
                      "posH"            :58,
                      "posW"            :47,
                      "posX"            :509,
                      "posY"            :16},
 "silenced_anim"    :{"customX1"        :-14,
                      "customX2"        :-41,
                      "customY1"        :0,
                      "customY2"        :-34,
                      "delay"           :0,
                      "delay_replay"    :0,
                      "delay_replay_end":0,
                      "foreground"      :false,
                      "outline"         :false,
                      "posH"            :58,
                      "posW"            :47,
                      "posX"            :509,
                      "posY"            :16},
 "sniper_anim"      :{"customX1"        :-14,
                      "customX2"        :-41,
                      "customY1"        :0,
                      "customY2"        :-34,
                      "delay"           :0,
                      "delay_replay"    :0,
                      "delay_replay_end":0,
                      "foreground"      :false,
                      "outline"         :false,
                      "posH"            :58,
                      "posW"            :47,
                      "posX"            :509,
                      "posY"            :16},
 "spraycan_anim"    :{"customX1"        :-14,
                      "customX2"        :-41,
                      "customY1"        :0,
                      "customY2"        :-34,
                      "delay"           :0,
                      "delay_replay"    :0,
                      "delay_replay_end":0,
                      "foreground"      :false,
                      "outline"         :false,
                      "posH"            :58,
                      "posW"            :47,
                      "posX"            :509,
                      "posY"            :16},
 "teargas_anim"     :{"customX1"        :-14,
                      "customX2"        :-41,
                      "customY1"        :0,
                      "customY2"        :-34,
                      "delay"           :0,
                      "delay_replay"    :0,
                      "delay_replay_end":0,
                      "foreground"      :false,
                      "outline"         :false,
                      "posH"            :58,
                      "posW"            :47,
                      "posX"            :509,
                      "posY"            :16},
 "tec9_anim"        :{"customX1"        :-14,
                      "customX2"        :-41,
                      "customY1"        :0,
                      "customY2"        :-34,
                      "delay"           :0,
                      "delay_replay"    :0,
                      "delay_replay_end":0,
                      "foreground"      :false,
                      "outline"         :false,
                      "posH"            :58,
                      "posW"            :47,
                      "posX"            :509,
                      "posY"            :16}}